{"users":[{"id":"user-7271167","gravatar_id":"5166db3dc642db0af9e3f1a8155d18e6","username":"time4popcorn","login":"time4popcorn","name":null,"fullname":null,"location":null,"language":"JavaScript","type":"user","public_repo_count":5,"repos":5,"followers":730,"followers_count":730,"score":1.0,"created_at":"2014-04-12T08:42:59Z","created":"2014-04-12T08:42:59Z"},{"id":"user-353790","gravatar_id":"682b7a49f9ed567186c4d1f707fe4523","username":"markjaquith","login":"markjaquith","name":"Mark Jaquith","fullname":"Mark Jaquith","location":"Tampa, FL","language":"PHP","type":"user","public_repo_count":58,"repos":58,"followers":730,"followers_count":730,"score":1.0,"created_at":"2010-08-04T08:49:03Z","created":"2010-08-04T08:49:03Z"},{"id":"user-14953","gravatar_id":"26104e0dd009885a029706bed0160bce","username":"gregkh","login":"gregkh","name":"Greg Kroah-Hartman","fullname":"Greg Kroah-Hartman","location":null,"language":"C","type":"user","public_repo_count":45,"repos":45,"followers":726,"followers_count":726,"score":1.0,"created_at":"2008-06-25T05:46:49Z","created":"2008-06-25T05:46:49Z"},{"id":"user-166834","gravatar_id":"e2e776d3d6fbc6a6b7e4c692bd080595","username":"aheckmann","login":"aheckmann","name":"Aaron Heckmann","fullname":"Aaron Heckmann","location":"Santa Clara, CA","language":"JavaScript","type":"user","public_repo_count":80,"repos":80,"followers":726,"followers_count":726,"score":1.0,"created_at":"2009-12-13T03:02:46Z","created":"2009-12-13T03:02:46Z"},{"id":"user-165401","gravatar_id":"7999d1e32e2c309b0e75b96a7125218a","username":"rogerwang","login":"rogerwang","name":"Roger Wang","fullname":"Roger Wang","location":"Shanghai, China","language":"C++","type":"user","public_repo_count":21,"repos":21,"followers":724,"followers_count":724,"score":1.0,"created_at":"2009-12-10T07:51:41Z","created":"2009-12-10T07:51:41Z"},{"id":"user-59852","gravatar_id":"e5852a88a22128ad80f78a1c4f20ca1c","username":"padolsey","login":"padolsey","name":"James Padolsey","fullname":"James Padolsey","location":"London, UK, Europe","language":"JavaScript","type":"user","public_repo_count":51,"repos":51,"followers":721,"followers_count":721,"score":1.0,"created_at":"2009-03-03T20:55:39Z","created":"2009-03-03T20:55:39Z"},{"id":"user-83844","gravatar_id":"466ef7561a0b100dc5a1021959962d28","username":"nvie","login":"nvie","name":"Vincent Driessen","fullname":"Vincent Driessen","location":"Netherlands","language":"Python","type":"user","public_repo_count":99,"repos":99,"followers":719,"followers_count":719,"score":1.0,"created_at":"2009-05-12T21:19:38Z","created":"2009-05-12T21:19:38Z"},{"id":"user-432536","gravatar_id":"cac992bb300ed4f3ed5c2a6049e552f9","username":"jspahrsummers","login":"jspahrsummers","name":"Justin Spahr-Summers","fullname":"Justin Spahr-Summers","location":"San Francisco, CA","language":"Objective-C","type":"user","public_repo_count":34,"repos":34,"followers":714,"followers_count":714,"score":1.0,"created_at":"2010-10-08T15:39:49Z","created":"2010-10-08T15:39:49Z"},{"id":"user-1627","gravatar_id":"992fe8c19bbbc27f2b562a9f96efc03d","username":"jamis","login":"jamis","name":"Jamis Buck","fullname":"Jamis Buck","location":"Caldwell, Idaho, USA","language":"Ruby","type":"user","public_repo_count":44,"repos":44,"followers":712,"followers_count":712,"score":1.0,"created_at":"2008-02-28T17:37:32Z","created":"2008-02-28T17:37:32Z"},{"id":"user-2911","gravatar_id":"af54a0871600db7fbdbb5c558a6e29a3","username":"mperham","login":"mperham","name":"Mike Perham","fullname":"Mike Perham","location":"Portland, OR","language":"Ruby","type":"user","public_repo_count":56,"repos":56,"followers":710,"followers_count":710,"score":1.0,"created_at":"2008-03-12T15:57:34Z","created":"2008-03-12T15:57:34Z"},{"id":"user-95136","gravatar_id":"1fe64ebb176498be5f73ab51986c6b7b","username":"davidfowl","login":"davidfowl","name":"David Fowler","fullname":"David Fowler","location":"Bellevue, WA","language":"C#","type":"user","public_repo_count":53,"repos":53,"followers":709,"followers_count":709,"score":1.0,"created_at":"2009-06-13T22:27:06Z","created":"2009-06-13T22:27:06Z"},{"id":"user-439401","gravatar_id":"7894bbdf1c05b18a1444ad8c76c9d583","username":"stof","login":"stof","name":"Christophe Coevoet","fullname":"Christophe Coevoet","location":"Paris","language":"PHP","type":"user","public_repo_count":147,"repos":147,"followers":708,"followers_count":708,"score":1.0,"created_at":"2010-10-14T13:56:42Z","created":"2010-10-14T13:56:42Z"},{"id":"user-204531","gravatar_id":"b29d0ca1377102cc591655a5c8bd7f85","username":"CakeDC","login":"CakeDC","name":"Cake Development Corporation","fullname":"Cake Development Corporation","location":"Las Vegas, Nevada","language":"PHP","type":"user","public_repo_count":21,"repos":21,"followers":707,"followers_count":707,"score":1.0,"created_at":"2010-02-16T11:06:50Z","created":"2010-02-16T11:06:50Z"},{"id":"user-333270","gravatar_id":"ac48abfd9468edd1d29f1c97c981e5f5","username":"Cocoanetics","login":"Cocoanetics","name":"Oliver Drobnik","fullname":"Oliver Drobnik","location":"Weistrach, Austria","language":"Objective-C","type":"user","public_repo_count":32,"repos":32,"followers":707,"followers_count":707,"score":1.0,"created_at":"2010-07-15T17:54:30Z","created":"2010-07-15T17:54:30Z"},{"id":"user-20723","gravatar_id":"f63068d724b6084f4807a86426b3b9eb","username":"audreyt","login":"audreyt","name":"唐鳳","fullname":"唐鳳","location":"Taipei, Taiwan","language":"Perl","type":"user","public_repo_count":206,"repos":206,"followers":704,"followers_count":704,"score":1.0,"created_at":"2008-08-14T21:19:26Z","created":"2008-08-14T21:19:26Z"},{"id":"user-549365","gravatar_id":"0530b4a11dcb32135b0d219109b7c2c1","username":"SimonVT","login":"SimonVT","name":"Simon Vig Therkildsen","fullname":"Simon Vig Therkildsen","location":"Denmark","language":"Java","type":"user","public_repo_count":16,"repos":16,"followers":703,"followers_count":703,"score":1.0,"created_at":"2011-01-05T22:02:28Z","created":"2011-01-05T22:02:28Z"},{"id":"user-1680","gravatar_id":"ae14cc4491ac334f9cd23f9f93b4305e","username":"orderedlist","login":"orderedlist","name":"Steve Smith","fullname":"Steve Smith","location":"South Bend, IN, USA","language":"Ruby","type":"user","public_repo_count":15,"repos":15,"followers":702,"followers_count":702,"score":1.0,"created_at":"2008-02-29T01:15:34Z","created":"2008-02-29T01:15:34Z"},{"id":"user-88061","gravatar_id":"eb42ff31986f5ed1d97580819134d702","username":"igorw","login":"igorw","name":"Igor Wiedler","fullname":"Igor Wiedler","location":"Berlin","language":"PHP","type":"user","public_repo_count":112,"repos":112,"followers":701,"followers_count":701,"score":1.0,"created_at":"2009-05-24T15:32:50Z","created":"2009-05-24T15:32:50Z"},{"id":"user-22064","gravatar_id":"b6b704f26ffe0d91e6317a1c069d4303","username":"johnmyleswhite","login":"johnmyleswhite","name":"John Myles White","fullname":"John Myles White","location":"San Francisco, CA","language":"Julia","type":"user","public_repo_count":165,"repos":165,"followers":693,"followers_count":693,"score":1.0,"created_at":"2008-08-26T16:24:56Z","created":"2008-08-26T16:24:56Z"},{"id":"user-1540855","gravatar_id":"724beed2464be3366cf8697d9c0b7268","username":"oschina","login":"oschina","name":"开源中国","fullname":"开源中国","location":"SZ China","language":"Java","type":"user","public_repo_count":8,"repos":8,"followers":693,"followers_count":693,"score":1.0,"created_at":"2012-03-15T15:29:19Z","created":"2012-03-15T15:29:19Z"},{"id":"user-108380","gravatar_id":"e7526ec3e801f8ba99f6746498a154a6","username":"rakyll","login":"rakyll","name":"Burcu Dogan","fullname":"Burcu Dogan","location":"San Francisco, CA","language":"JavaScript","type":"user","public_repo_count":76,"repos":76,"followers":692,"followers_count":692,"score":1.0,"created_at":"2009-07-24T16:35:06Z","created":"2009-07-24T16:35:06Z"},{"id":"user-639601","gravatar_id":"dc13d329db98a4ff44d52013b80e3bf4","username":"zcbenz","login":"zcbenz","name":"Cheng Zhao","fullname":"Cheng Zhao","location":"Beijing, China","language":"JavaScript","type":"user","public_repo_count":40,"repos":40,"followers":686,"followers_count":686,"score":1.0,"created_at":"2011-02-26T14:16:12Z","created":"2011-02-26T14:16:12Z"},{"id":"user-42793","gravatar_id":"2bb2258c02ee8f25f1a41a6223f9ac1f","username":"vmg","login":"vmg","name":"Vicent Marti","fullname":"Vicent Marti","location":"Europe","language":"C","type":"user","public_repo_count":43,"repos":43,"followers":682,"followers_count":682,"score":1.0,"created_at":"2008-12-26T20:21:00Z","created":"2008-12-26T20:21:00Z"},{"id":"user-33886","gravatar_id":"097f39f4cd9a83a03d92c246a2797880","username":"kriswallsmith","login":"kriswallsmith","name":"Kris Wallsmith","fullname":"Kris Wallsmith","location":"Portland, Oregon USA","language":"PHP","type":"user","public_repo_count":45,"repos":45,"followers":680,"followers_count":680,"score":1.0,"created_at":"2008-11-11T18:29:49Z","created":"2008-11-11T18:29:49Z"},{"id":"user-1671","gravatar_id":"3853788896fe7234d126dd3b7576d47a","username":"scrooloose","login":"scrooloose","name":"Martin Grenfell","fullname":"Martin Grenfell","location":"UK","language":"VimL","type":"user","public_repo_count":36,"repos":36,"followers":680,"followers_count":680,"score":1.0,"created_at":"2008-02-29T00:12:11Z","created":"2008-02-29T00:12:11Z"},{"id":"user-4433","gravatar_id":"afd18bf247216624bd5fdd1b112f0b48","username":"jed","login":"jed","name":"Jed Schmidt","fullname":"Jed Schmidt","location":"Brooklyn, NYC","language":"JavaScript","type":"user","public_repo_count":43,"repos":43,"followers":678,"followers_count":678,"score":1.0,"created_at":"2008-04-03T03:12:49Z","created":"2008-04-03T03:12:49Z"},{"id":"user-208827","gravatar_id":"a397a02e62916831379b915a0b5a3a9d","username":"honcheng","login":"honcheng","name":"honcheng","fullname":"honcheng","location":"Singapore","language":"Objective-C","type":"user","public_repo_count":46,"repos":46,"followers":678,"followers_count":678,"score":1.0,"created_at":"2010-02-23T01:18:23Z","created":"2010-02-23T01:18:23Z"},{"id":"user-22","gravatar_id":"0d949b795e64e062c4c001c6f5a6f3f3","username":"macournoyer","login":"macournoyer","name":"Marc-André Cournoyer","fullname":"Marc-André Cournoyer","location":"Montreal, QC, Canada","language":"Ruby","type":"user","public_repo_count":51,"repos":51,"followers":676,"followers_count":676,"score":1.0,"created_at":"2008-01-14T10:49:35Z","created":"2008-01-14T10:49:35Z"},{"id":"user-490265","gravatar_id":"af22ed6bb242a2a308ea74414a14e9ca","username":"qiao","login":"qiao","name":"Xueqiao Xu","fullname":"Xueqiao Xu","location":"Mountain View, CA","language":"JavaScript","type":"user","public_repo_count":31,"repos":31,"followers":676,"followers_count":676,"score":1.0,"created_at":"2010-11-21T02:51:32Z","created":"2010-11-21T02:51:32Z"},{"id":"user-1919","gravatar_id":"1f283e06dbdff08f4f1df21cb2e102cf","username":"bobuk","login":"bobuk","name":"Grigory Bakunov","fullname":"Grigory Bakunov","location":"Russia, Moscow","language":"Python","type":"user","public_repo_count":29,"repos":29,"followers":675,"followers_count":675,"score":1.0,"created_at":"2008-03-01T23:24:20Z","created":"2008-03-01T23:24:20Z"},{"id":"user-32314","gravatar_id":"69a180136f3c237769452a4af0bbb9a1","username":"tmcw","login":"tmcw","name":"Tom MacWright","fullname":"Tom MacWright","location":"Washington, DC","language":"JavaScript","type":"user","public_repo_count":227,"repos":227,"followers":674,"followers_count":674,"score":1.0,"created_at":"2008-11-02T23:44:49Z","created":"2008-11-02T23:44:49Z"},{"id":"user-55448","gravatar_id":"f45e91dd77297a2ff3eddc1881e64d20","username":"robbin","login":"robbin","name":"Robin Fan","fullname":"Robin Fan","location":"Shanghai, China","language":"Ruby","type":"user","public_repo_count":10,"repos":10,"followers":673,"followers_count":673,"score":1.0,"created_at":"2009-02-18T03:38:19Z","created":"2009-02-18T03:38:19Z"},{"id":"user-163390","gravatar_id":"eb827b39e830eff658fe84a7fbd9af84","username":"grp","login":"grp","name":"Grant Paul","fullname":"Grant Paul","location":"","language":"C","type":"user","public_repo_count":19,"repos":19,"followers":673,"followers_count":673,"score":1.0,"created_at":"2009-12-06T18:51:41Z","created":"2009-12-06T18:51:41Z"},{"id":"user-631369","gravatar_id":"8209444173472be8823f570f77ed8b8b","username":"nrrrdcore","login":"nrrrdcore","name":"Julie Ann Horvath","fullname":"Julie Ann Horvath","location":"San Francisco, CA","language":"JavaScript","type":"user","public_repo_count":21,"repos":21,"followers":672,"followers_count":672,"score":1.0,"created_at":"2011-02-22T06:05:38Z","created":"2011-02-22T06:05:38Z"},{"id":"user-236886","gravatar_id":"b64a1aa6e718d317ddd92ac42888a5da","username":"tavisrudd","login":"tavisrudd","name":"Tavis Rudd","fullname":"Tavis Rudd","location":"Vancouver","language":"Clojure","type":"user","public_repo_count":129,"repos":129,"followers":670,"followers_count":670,"score":1.0,"created_at":"2010-04-04T22:16:08Z","created":"2010-04-04T22:16:08Z"},{"id":"user-24086","gravatar_id":"669144d1ab0a861af5d54175371bc586","username":"markstory","login":"markstory","name":"Mark Story","fullname":"Mark Story","location":"Toronto, Ontario","language":"PHP","type":"user","public_repo_count":41,"repos":41,"followers":669,"followers_count":669,"score":1.0,"created_at":"2008-09-11T02:52:38Z","created":"2008-09-11T02:52:38Z"},{"id":"user-499550","gravatar_id":"eca93da2c67aadafe35d477aa8f454b8","username":"yyx990803","login":"yyx990803","name":"Evan You","fullname":"Evan You","location":"New York / Wuxi, China","language":"JavaScript","type":"user","public_repo_count":57,"repos":57,"followers":669,"followers_count":669,"score":1.0,"created_at":"2010-11-28T01:05:40Z","created":"2010-11-28T01:05:40Z"},{"id":"user-2527933","gravatar_id":"81b58502541f9445253f30497e53c280","username":"SaraSoueidan","login":"SaraSoueidan","name":"Sara Soueidan","fullname":"Sara Soueidan","location":"Lebanon","language":"JavaScript","type":"user","public_repo_count":12,"repos":12,"followers":668,"followers_count":668,"score":1.0,"created_at":"2012-10-10T11:53:40Z","created":"2012-10-10T11:53:40Z"},{"id":"user-9265","gravatar_id":"81eec7f220df03d5b8cadf106a2c14c5","username":"jcoglan","login":"jcoglan","name":"James Coglan","fullname":"James Coglan","location":"","language":"Ruby","type":"user","public_repo_count":104,"repos":104,"followers":663,"followers_count":663,"score":1.0,"created_at":"2008-05-04T14:39:21Z","created":"2008-05-04T14:39:21Z"},{"id":"user-181635","gravatar_id":"21dbcdbf46f8ee3774c1b9b3efadfa9e","username":"tbranyen","login":"tbranyen","name":"Tim Branyen","fullname":"Tim Branyen","location":"Boston, MA","language":"JavaScript","type":"user","public_repo_count":133,"repos":133,"followers":660,"followers_count":660,"score":1.0,"created_at":"2010-01-13T18:55:44Z","created":"2010-01-13T18:55:44Z"},{"id":"user-297042","gravatar_id":"92dfeb863138a5a9c0453ed80f9c8c75","username":"pamelafox","login":"pamelafox","name":"Pamela Fox","fullname":"Pamela Fox","location":null,"language":"JavaScript","type":"user","public_repo_count":46,"repos":46,"followers":657,"followers_count":657,"score":1.0,"created_at":"2010-06-05T00:29:54Z","created":"2010-06-05T00:29:54Z"},{"id":"user-24734","gravatar_id":"9112400090829f79d97ed9b12056fa4f","username":"matthewmccullough","login":"matthewmccullough","name":"Matthew McCullough","fullname":"Matthew McCullough","location":"Denver, CO USA","language":"Java","type":"user","public_repo_count":50,"repos":50,"followers":656,"followers_count":656,"score":1.0,"created_at":"2008-09-15T20:54:43Z","created":"2008-09-15T20:54:43Z"},{"id":"user-1610572","gravatar_id":"4a70a247b4f222894f6b9861e40f733d","username":"hcilab","login":"hcilab","name":"Account for Github research","fullname":"Account for Github research","location":"","language":"Go","type":"user","public_repo_count":2,"repos":2,"followers":655,"followers_count":655,"score":1.0,"created_at":"2012-04-04T05:12:28Z","created":"2012-04-04T05:12:28Z"},{"id":"user-28185","gravatar_id":"bc5a05e7a6824f0b9aa95d9b7a0b8beb","username":"malsup","login":"malsup","name":"Mike Alsup","fullname":"Mike Alsup","location":"@malsup on twitter","language":"JavaScript","type":"user","public_repo_count":15,"repos":15,"followers":655,"followers_count":655,"score":1.0,"created_at":"2008-10-09T00:38:42Z","created":"2008-10-09T00:38:42Z"},{"id":"user-202642","gravatar_id":"63c59020e0d7efaef816653c853ecc05","username":"alganet","login":"alganet","name":"Alexandre Gomes Gaigalas","fullname":"Alexandre Gomes Gaigalas","location":"São Paulo, SP, Brasil","language":"PHP","type":"user","public_repo_count":39,"repos":39,"followers":655,"followers_count":655,"score":1.0,"created_at":"2010-02-12T18:48:51Z","created":"2010-02-12T18:48:51Z"},{"id":"user-993322","gravatar_id":"f5897d0a3ee1c390cce0da65e08044e9","username":"qiangxue","login":"qiangxue","name":"Qiang Xue","fullname":"Qiang Xue","location":"Virginia, U.S.A.","language":"PHP","type":"user","public_repo_count":0,"repos":0,"followers":655,"followers_count":655,"score":1.0,"created_at":"2011-08-20T20:09:30Z","created":"2011-08-20T20:09:30Z"},{"id":"user-583231","gravatar_id":"7194e8d48fa1d2b689f99443b767316c","username":"octocat","login":"octocat","name":"The Octocat","fullname":"The Octocat","location":"San Francisco","language":"CSS","type":"user","public_repo_count":5,"repos":5,"followers":653,"followers_count":653,"score":1.0,"created_at":"2011-01-25T18:44:36Z","created":"2011-01-25T18:44:36Z"},{"id":"user-317625","gravatar_id":"e5770fdf7c887878654caa894257200a","username":"Dinnerbone","login":"Dinnerbone","name":"Dinner Bone","fullname":"Dinner Bone","location":"Stockholm, Sweden","language":"Java","type":"user","public_repo_count":10,"repos":10,"followers":651,"followers_count":651,"score":1.0,"created_at":"2010-06-29T16:51:57Z","created":"2010-06-29T16:51:57Z"},{"id":"user-54641","gravatar_id":"e915a97db0aeef46c5dd899d47c175ad","username":"rlerdorf","login":"rlerdorf","name":"Rasmus Lerdorf","fullname":"Rasmus Lerdorf","location":"Probably on a plane","language":"C","type":"user","public_repo_count":37,"repos":37,"followers":648,"followers_count":648,"score":1.0,"created_at":"2009-02-15T02:31:07Z","created":"2009-02-15T02:31:07Z"},{"id":"user-93595","gravatar_id":"cceff469a14240fbdda75dfbee065388","username":"sergeche","login":"sergeche","name":"Sergey Chikuyonok","fullname":"Sergey Chikuyonok","location":"Moscow, Russia","language":"JavaScript","type":"user","public_repo_count":37,"repos":37,"followers":645,"followers_count":645,"score":1.0,"created_at":"2009-06-09T14:39:00Z","created":"2009-06-09T14:39:00Z"},{"id":"user-66836","gravatar_id":"13c60e2a5806406b537daa542d3495da","username":"flyerhzm","login":"flyerhzm","name":"Richard Huang","fullname":"Richard Huang","location":"Shanghai, China","language":"Ruby","type":"user","public_repo_count":87,"repos":87,"followers":644,"followers_count":644,"score":1.0,"created_at":"2009-03-25T03:42:43Z","created":"2009-03-25T03:42:43Z"},{"id":"user-13760","gravatar_id":"62e8c8bfaa8d755cab82accb48d335c8","username":"joshaber","login":"joshaber","name":"Josh Abernathy","fullname":"Josh Abernathy","location":"Yellow Springs, OH","language":"Objective-C","type":"user","public_repo_count":33,"repos":33,"followers":641,"followers_count":641,"score":1.0,"created_at":"2008-06-15T00:25:05Z","created":"2008-06-15T00:25:05Z"},{"id":"user-304657","gravatar_id":"9c51a8b8afa2366a2ef4650c411f187a","username":"ekmett","login":"ekmett","name":"Edward Kmett","fullname":"Edward Kmett","location":"Cambridge, MA","language":"Haskell","type":"user","public_repo_count":170,"repos":170,"followers":641,"followers_count":641,"score":1.0,"created_at":"2010-06-14T08:43:12Z","created":"2010-06-14T08:43:12Z"},{"id":"user-1228","gravatar_id":"04d6b8e8d3c68899ac88eb8623392150","username":"ericflo","login":"ericflo","name":"Eric Florenzano","fullname":"Eric Florenzano","location":"San Francisco, CA","language":"Python","type":"user","public_repo_count":40,"repos":40,"followers":639,"followers_count":639,"score":1.0,"created_at":"2008-02-27T22:50:28Z","created":"2008-02-27T22:50:28Z"},{"id":"user-13718","gravatar_id":"4df117a6ebd831e630e1e1786159bfa5","username":"brandonaaron","login":"brandonaaron","name":"Brandon Aaron","fullname":"Brandon Aaron","location":"","language":"JavaScript","type":"user","public_repo_count":50,"repos":50,"followers":639,"followers_count":639,"score":1.0,"created_at":"2008-06-14T14:26:57Z","created":"2008-06-14T14:26:57Z"},{"id":"user-104009","gravatar_id":"20171a64471be602e50c8ba7662313af","username":"loopj","login":"loopj","name":"James Smith","fullname":"James Smith","location":"San Francisco, CA","language":"JavaScript","type":"user","public_repo_count":38,"repos":38,"followers":636,"followers_count":636,"score":1.0,"created_at":"2009-07-11T23:01:25Z","created":"2009-07-11T23:01:25Z"},{"id":"user-275871","gravatar_id":"3d43d9038ab645ecb2e3a1df2951d30a","username":"bnoordhuis","login":"bnoordhuis","name":"Ben Noordhuis","fullname":"Ben Noordhuis","location":"Gouda, the Netherlands","language":"C","type":"user","public_repo_count":92,"repos":92,"followers":635,"followers_count":635,"score":1.0,"created_at":"2010-05-13T20:10:19Z","created":"2010-05-13T20:10:19Z"},{"id":"user-313317","gravatar_id":"c936d5fc7ef09504480b9d8aafb7e8a0","username":"BrendanEich","login":"BrendanEich","name":"Brendan Eich","fullname":"Brendan Eich","location":null,"language":"JavaScript","type":"user","public_repo_count":2,"repos":2,"followers":635,"followers_count":635,"score":1.0,"created_at":"2010-06-24T04:39:24Z","created":"2010-06-24T04:39:24Z"},{"id":"user-12104","gravatar_id":"0ec58a040e1e4e959c8566484b4bba19","username":"masuidrive","login":"masuidrive","name":"Yuichiro MASUI","fullname":"Yuichiro MASUI","location":"Tokyo, Japan","language":"JavaScript","type":"user","public_repo_count":41,"repos":41,"followers":634,"followers_count":634,"score":1.0,"created_at":"2008-05-31T20:15:07Z","created":"2008-05-31T20:15:07Z"},{"id":"user-9004","gravatar_id":"19e786a2a74377ff6e052d87fd8d1fa8","username":"xdite","login":"xdite","name":"Yi-Ting Cheng","fullname":"Yi-Ting Cheng","location":"Taipei, Taiwan / San Francisco","language":"Ruby","type":"user","public_repo_count":117,"repos":117,"followers":634,"followers_count":634,"score":1.0,"created_at":"2008-05-01T07:21:50Z","created":"2008-05-01T07:21:50Z"},{"id":"user-12732","gravatar_id":"c86443373fbfe92996aa882d0d7a59f8","username":"imathis","login":"imathis","name":"Brandon Mathis","fullname":"Brandon Mathis","location":"Birmingham, AL","language":"Ruby","type":"user","public_repo_count":44,"repos":44,"followers":630,"followers_count":630,"score":1.0,"created_at":"2008-06-05T18:42:36Z","created":"2008-06-05T18:42:36Z"},{"id":"user-113","gravatar_id":"c69521d6e22fc0bbd69337ec8b1698df","username":"mattetti","login":"mattetti","name":"Matt Aimonetti","fullname":"Matt Aimonetti","location":"Santa Monica, CA","language":"Ruby","type":"user","public_repo_count":201,"repos":201,"followers":630,"followers_count":630,"score":1.0,"created_at":"2008-01-31T22:56:31Z","created":"2008-01-31T22:56:31Z"},{"id":"user-257","gravatar_id":"a82ba1167f4d4a8d1de63820e576a87f","username":"robbyrussell","login":"robbyrussell","name":"Robby Russell","fullname":"Robby Russell","location":"Portland, Oregon","language":"Ruby","type":"user","public_repo_count":26,"repos":26,"followers":628,"followers_count":628,"score":1.0,"created_at":"2008-02-13T23:04:43Z","created":"2008-02-13T23:04:43Z"},{"id":"user-559654","gravatar_id":"b45dac4e52795ea2c8c493612d09ac32","username":"soyjavi","login":"soyjavi","name":"Javi Jiménez","fullname":"Javi Jiménez","location":"Bilbao, ES","language":"JavaScript","type":"user","public_repo_count":41,"repos":41,"followers":627,"followers_count":627,"score":1.0,"created_at":"2011-01-12T14:16:30Z","created":"2011-01-12T14:16:30Z"},{"id":"user-31945","gravatar_id":"2735068c913a072744a799e3c0833b7b","username":"fredwu","login":"fredwu","name":"Fred Wu","fullname":"Fred Wu","location":"Melbourne, Australia (Shanghai, China)","language":"Ruby","type":"user","public_repo_count":81,"repos":81,"followers":626,"followers_count":626,"score":1.0,"created_at":"2008-10-31T04:34:48Z","created":"2008-10-31T04:34:48Z"},{"id":"user-7","gravatar_id":"540cb3b3712ffe045113cb03bab616a2","username":"evanphx","login":"evanphx","name":"Evan Phoenix","fullname":"Evan Phoenix","location":"Los Angeles, CA","language":"Ruby","type":"user","public_repo_count":96,"repos":96,"followers":625,"followers_count":625,"score":1.0,"created_at":"2008-01-12T16:46:24Z","created":"2008-01-12T16:46:24Z"},{"id":"user-10135","gravatar_id":"f1d37642fdaa1662ff46e4c65731e9ab","username":"headius","login":"headius","name":"Charles Oliver Nutter","fullname":"Charles Oliver Nutter","location":null,"language":"Ruby","type":"user","public_repo_count":133,"repos":133,"followers":625,"followers_count":625,"score":1.0,"created_at":"2008-05-13T06:03:09Z","created":"2008-05-13T06:03:09Z"},{"id":"user-773569","gravatar_id":"d3b61bf864967bf2ae57e7facfa08303","username":"vczh","login":"vczh","name":"Zihan Chen","fullname":"Zihan Chen","location":"Beijing, China","language":"C++","type":"user","public_repo_count":7,"repos":7,"followers":624,"followers_count":624,"score":1.0,"created_at":"2011-05-07T08:30:48Z","created":"2011-05-07T08:30:48Z"},{"id":"user-32551","gravatar_id":"05243ae612fb4dcfb151e08489f334b0","username":"davglass","login":"davglass","name":"Dav Glass","fullname":"Dav Glass","location":"Marion, IL","language":"JavaScript","type":"user","public_repo_count":188,"repos":188,"followers":622,"followers_count":622,"score":1.0,"created_at":"2008-11-04T04:22:29Z","created":"2008-11-04T04:22:29Z"},{"id":"user-416209","gravatar_id":"cff733cf90823edd218a834980379c61","username":"thomasdavis","login":"thomasdavis","name":"Thomas Davis","fullname":"Thomas Davis","location":"Brisbane, Australia","language":"JavaScript","type":"user","public_repo_count":102,"repos":102,"followers":622,"followers_count":622,"score":1.0,"created_at":"2010-09-26T08:07:38Z","created":"2010-09-26T08:07:38Z"},{"id":"user-46677","gravatar_id":"e30754b725a8b734f1a507beac3063c6","username":"r00k","login":"r00k","name":"Ben Orenstein","fullname":"Ben Orenstein","location":"Boston, MA","language":"Ruby","type":"user","public_repo_count":58,"repos":58,"followers":620,"followers_count":620,"score":1.0,"created_at":"2009-01-15T01:59:49Z","created":"2009-01-15T01:59:49Z"},{"id":"user-61148","gravatar_id":"9400cb5aeb155ccec614652542fd274d","username":"balupton","login":"balupton","name":"Benjamin Arthur Lupton","fullname":"Benjamin Arthur Lupton","location":"Sydney, Australia","language":"JavaScript","type":"user","public_repo_count":140,"repos":140,"followers":619,"followers_count":619,"score":1.0,"created_at":"2009-03-07T21:43:06Z","created":"2009-03-07T21:43:06Z"},{"id":"user-199","gravatar_id":"24d2f8804e6bb4b7ea6bd11e0a586470","username":"jeremy","login":"jeremy","name":"Jeremy Kemper","fullname":"Jeremy Kemper","location":"Scottsdale, AZ","language":"Ruby","type":"user","public_repo_count":53,"repos":53,"followers":616,"followers_count":616,"score":1.0,"created_at":"2008-02-13T03:02:19Z","created":"2008-02-13T03:02:19Z"},{"id":"user-1223348","gravatar_id":"119624ee925a4d35e1221ecf8a30338e","username":"nostra13","login":"nostra13","name":"Sergey Tarasevich","fullname":"Sergey Tarasevich","location":"Hrodna, Belarus","language":"Java","type":"user","public_repo_count":2,"repos":2,"followers":614,"followers_count":614,"score":1.0,"created_at":"2011-11-27T14:47:56Z","created":"2011-11-27T14:47:56Z"},{"id":"user-2946214","gravatar_id":"f10e66389e4015051bd94482f6f9b4e6","username":"Unknwon","login":"Unknwon","name":"无闻","fullname":"无闻","location":"Boston, MA","language":"Go","type":"user","public_repo_count":24,"repos":24,"followers":614,"followers_count":614,"score":1.0,"created_at":"2012-12-02T20:02:58Z","created":"2012-12-02T20:02:58Z"},{"id":"user-47517","gravatar_id":"c5edb8ac42268961073ce12297a871f4","username":"comex","login":"comex","name":null,"fullname":null,"location":null,"language":"C","type":"user","public_repo_count":49,"repos":49,"followers":611,"followers_count":611,"score":1.0,"created_at":"2009-01-18T20:21:26Z","created":"2009-01-18T20:21:26Z"},{"id":"user-872655","gravatar_id":"34bfefd91212b1ef064d6577ce0bc6a9","username":"codefollower","login":"codefollower","name":null,"fullname":null,"location":null,"language":"Java","type":"user","public_repo_count":13,"repos":13,"followers":607,"followers_count":607,"score":1.0,"created_at":"2011-06-24T06:25:56Z","created":"2011-06-24T06:25:56Z"},{"id":"user-97422","gravatar_id":"f76041410752f9019752b6afd2bebc2a","username":"jwage","login":"jwage","name":"Jonathan H. Wage","fullname":"Jonathan H. Wage","location":"Nashville, TN","language":"PHP","type":"user","public_repo_count":7,"repos":7,"followers":604,"followers_count":604,"score":1.0,"created_at":"2009-06-21T00:37:00Z","created":"2009-06-21T00:37:00Z"},{"id":"user-53024","gravatar_id":"004518b2a8e91d0054a756ee4c425a9d","username":"tianyicui","login":"tianyicui","name":"Tianyi Cui","fullname":"Tianyi Cui","location":"Hong Kong","language":"Ruby","type":"user","public_repo_count":60,"repos":60,"followers":601,"followers_count":601,"score":1.0,"created_at":"2009-02-09T14:50:20Z","created":"2009-02-09T14:50:20Z"},{"id":"user-50003","gravatar_id":"0cb9832a01c22c083390f3c5dcb64105","username":"kohsuke","login":"kohsuke","name":"Kohsuke Kawaguchi","fullname":"Kohsuke Kawaguchi","location":"San Jose, California","language":"Java","type":"user","public_repo_count":152,"repos":152,"followers":599,"followers_count":599,"score":1.0,"created_at":"2009-01-28T18:53:21Z","created":"2009-01-28T18:53:21Z"},{"id":"user-984","gravatar_id":"b61ce134adf2d6eb1d1f1d11122d6142","username":"phlipper","login":"phlipper","name":"Phil Cohen","fullname":"Phil Cohen","location":"Near Lake Tahoe, CA","language":"Ruby","type":"user","public_repo_count":214,"repos":214,"followers":599,"followers_count":599,"score":1.0,"created_at":"2008-02-26T19:58:08Z","created":"2008-02-26T19:58:08Z"},{"id":"user-4919","gravatar_id":"2ee45d7dd2c26c6fea3b887f831f7b38","username":"aaronsw","login":"aaronsw","name":"Aaron Swartz","fullname":"Aaron Swartz","location":null,"language":"Python","type":"user","public_repo_count":27,"repos":27,"followers":598,"followers_count":598,"score":1.0,"created_at":"2008-04-04T04:19:03Z","created":"2008-04-04T04:19:03Z"},{"id":"user-1060","gravatar_id":"8ddbf811da78bb0daeeb3cacd7cf743f","username":"andrew","login":"andrew","name":"Andrew Nesbitt","fullname":"Andrew Nesbitt","location":"Bath, UK","language":"Ruby","type":"user","public_repo_count":163,"repos":163,"followers":598,"followers_count":598,"score":1.0,"created_at":"2008-02-27T11:39:22Z","created":"2008-02-27T11:39:22Z"},{"id":"user-173","gravatar_id":"20bfe76b3d6105641f879fe45cfc9272","username":"bkeepers","login":"bkeepers","name":"Brandon Keepers","fullname":"Brandon Keepers","location":"Holland, MI, US","language":"Ruby","type":"user","public_repo_count":64,"repos":64,"followers":596,"followers_count":596,"score":1.0,"created_at":"2008-02-09T16:42:49Z","created":"2008-02-09T16:42:49Z"},{"id":"user-794999","gravatar_id":"cb947f0ebdde8d0f973741b366a51ed6","username":"tholman","login":"tholman","name":"Tim Holman","fullname":"Tim Holman","location":"Australian... living in New York","language":"JavaScript","type":"user","public_repo_count":18,"repos":18,"followers":596,"followers_count":596,"score":1.0,"created_at":"2011-05-18T04:24:22Z","created":"2011-05-18T04:24:22Z"},{"id":"user-359395","gravatar_id":"598af081f6bf47a80e684ffd3175532e","username":"justjavac","login":"justjavac","name":"迷渡","fullname":"迷渡","location":"Tianjin, China","language":"JavaScript","type":"user","public_repo_count":17,"repos":17,"followers":594,"followers_count":594,"score":1.0,"created_at":"2010-08-10T05:24:31Z","created":"2010-08-10T05:24:31Z"},{"id":"user-329591","gravatar_id":"2c08a3eed709a9d1a2654cea45aa466f","username":"wesm","login":"wesm","name":"Wes McKinney","fullname":"Wes McKinney","location":"San Francisco, CA","language":"Python","type":"user","public_repo_count":32,"repos":32,"followers":593,"followers_count":593,"score":1.0,"created_at":"2010-07-12T13:24:25Z","created":"2010-07-12T13:24:25Z"},{"id":"user-65675","gravatar_id":"b069294dc48acd6c4cfe8b98fc467c89","username":"josegonzalez","login":"josegonzalez","name":"Jose Diaz-Gonzalez","fullname":"Jose Diaz-Gonzalez","location":"New York, NY","language":"PHP","type":"user","public_repo_count":256,"repos":256,"followers":592,"followers_count":592,"score":1.0,"created_at":"2009-03-22T03:10:46Z","created":"2009-03-22T03:10:46Z"},{"id":"user-1269537","gravatar_id":"159ac701239eff9f809e7560f6db2d8d","username":"turingou","login":"turingou","name":"Guo Yu","fullname":"Guo Yu","location":"Peking, Mainland China","language":"JavaScript","type":"user","public_repo_count":154,"repos":154,"followers":592,"followers_count":592,"score":1.0,"created_at":"2011-12-17T12:23:52Z","created":"2011-12-17T12:23:52Z"},{"id":"user-72919","gravatar_id":"a79ff2bb7da84e275361857d2feb2b1b","username":"cameronmcefee","login":"cameronmcefee","name":"Cameron McEfee","fullname":"Cameron McEfee","location":"San Francisco","language":"JavaScript","type":"user","public_repo_count":12,"repos":12,"followers":591,"followers_count":591,"score":1.0,"created_at":"2009-04-12T06:16:59Z","created":"2009-04-12T06:16:59Z"},{"id":"user-2449","gravatar_id":"ea39e564e226a87b507a00d46e471e10","username":"toastdriven","login":"toastdriven","name":"Daniel Lindsley","fullname":"Daniel Lindsley","location":"Lawrence, KS","language":"Python","type":"user","public_repo_count":93,"repos":93,"followers":589,"followers_count":589,"score":1.0,"created_at":"2008-03-06T20:05:39Z","created":"2008-03-06T20:05:39Z"},{"id":"user-498212","gravatar_id":"0ebf471a3ae8df42a84f93a7efbbdbd0","username":"AshFurrow","login":"AshFurrow","name":"Ash Furrow","fullname":"Ash Furrow","location":"Amsterdam","language":"Objective-C","type":"user","public_repo_count":76,"repos":76,"followers":589,"followers_count":589,"score":1.0,"created_at":"2010-11-26T18:46:10Z","created":"2010-11-26T18:46:10Z"},{"id":"user-797","gravatar_id":"4131d2f57a0db2a2b4d9a62bd389fd44","username":"tarcieri","login":"tarcieri","name":"Tony Arcieri","fullname":"Tony Arcieri","location":"San Francisco, CA","language":"Ruby","type":"user","public_repo_count":68,"repos":68,"followers":584,"followers_count":584,"score":1.0,"created_at":"2008-02-25T04:32:26Z","created":"2008-02-25T04:32:26Z"},{"id":"user-14498","gravatar_id":"f04edc7cb2099745e5413c754d3d22f5","username":"benoitc","login":"benoitc","name":"Benoit Chesneau","fullname":"Benoit Chesneau","location":"Creil, France","language":"Erlang","type":"user","public_repo_count":138,"repos":138,"followers":583,"followers_count":583,"score":1.0,"created_at":"2008-06-21T06:50:58Z","created":"2008-06-21T06:50:58Z"},{"id":"user-939409","gravatar_id":"778a5dacdd945389f839f44bcf55eb03","username":"freddix","login":"freddix","name":"Fryderyk Dziarmagowski","fullname":"Fryderyk Dziarmagowski","location":null,"language":"Shell","type":"user","public_repo_count":1244,"repos":1244,"followers":582,"followers_count":582,"score":1.0,"created_at":"2011-07-26T10:57:35Z","created":"2011-07-26T10:57:35Z"},{"id":"user-145203","gravatar_id":"43aa59f31939e9061ff78a57c3b176c6","username":"ioerror","login":"ioerror","name":"\\033]2;Jacob Appelbaum\\007","fullname":"\\033]2;Jacob Appelbaum\\007","location":null,"language":"C","type":"user","public_repo_count":77,"repos":77,"followers":575,"followers_count":575,"score":1.0,"created_at":"2009-10-27T10:20:32Z","created":"2009-10-27T10:20:32Z"},{"id":"user-311752","gravatar_id":"e7f4e4b1d3b381e70f864bc7f8b4493e","username":"ianstormtaylor","login":"ianstormtaylor","name":"Ian Storm Taylor","fullname":"Ian Storm Taylor","location":"San Francisco, CA","language":"JavaScript","type":"user","public_repo_count":131,"repos":131,"followers":574,"followers_count":574,"score":1.0,"created_at":"2010-06-22T13:42:12Z","created":"2010-06-22T13:42:12Z"},{"id":"user-12066","gravatar_id":"d47e5a6a94e793ad1a1c315d6ab63877","username":"henriquebastos","login":"henriquebastos","name":"Henrique Bastos","fullname":"Henrique Bastos","location":"Niterói, Brasil","language":"Python","type":"user","public_repo_count":69,"repos":69,"followers":572,"followers_count":572,"score":1.0,"created_at":"2008-05-31T13:09:10Z","created":"2008-05-31T13:09:10Z"},{"id":"user-781659","gravatar_id":"56c4053438af8e8b90d6f53cbb7573be","username":"jakevdp","login":"jakevdp","name":"Jake Vanderplas","fullname":"Jake Vanderplas","location":"Seattle WA","language":"Python","type":"user","public_repo_count":76,"repos":76,"followers":572,"followers_count":572,"score":1.0,"created_at":"2011-05-11T14:39:53Z","created":"2011-05-11T14:39:53Z"},{"id":"user-75607","gravatar_id":"242a4a40838ce152d5fabb7643c0e744","username":"suissa","login":"suissa","name":"Jean Carlo Nascimento","fullname":"Jean Carlo Nascimento","location":"São Paulo - SP","language":"JavaScript","type":"user","public_repo_count":195,"repos":195,"followers":570,"followers_count":570,"score":1.0,"created_at":"2009-04-20T05:34:33Z","created":"2009-04-20T05:34:33Z"}]}